safe_autonomy_simulation/__init__.py
safe_autonomy_simulation/simulator.py
safe_autonomy_simulation/controls/__init__.py
safe_autonomy_simulation/controls/control_queue.py
safe_autonomy_simulation/controls/no_control.py
safe_autonomy_simulation/dynamics/__init__.py
safe_autonomy_simulation/dynamics/dynamics.py
safe_autonomy_simulation/dynamics/ode.py
safe_autonomy_simulation/dynamics/passthrough.py
safe_autonomy_simulation/dynamics/utils.py
safe_autonomy_simulation/entities/__init__.py
safe_autonomy_simulation/entities/entity.py
safe_autonomy_simulation/entities/integrator.py
safe_autonomy_simulation/entities/physical.py
safe_autonomy_simulation/entities/point.py
safe_autonomy_simulation/jax/__init__.py
safe_autonomy_simulation/jax/ode.py
safe_autonomy_simulation/materials/__init__.py
safe_autonomy_simulation/materials/common.py
safe_autonomy_simulation/materials/material.py
safe_autonomy_simulation/sims/__init__.py
safe_autonomy_simulation/sims/inspection/__init__.py
safe_autonomy_simulation/sims/inspection/camera.py
safe_autonomy_simulation/sims/inspection/inspection_points.py
safe_autonomy_simulation/sims/inspection/inspection_simulator.py
safe_autonomy_simulation/sims/inspection/inspector.py
safe_autonomy_simulation/sims/inspection/sun.py
safe_autonomy_simulation/sims/inspection/target.py
safe_autonomy_simulation/sims/inspection/utils/__init__.py
safe_autonomy_simulation/sims/inspection/utils/illumination.py
safe_autonomy_simulation/sims/inspection/utils/polar.py
safe_autonomy_simulation/sims/inspection/utils/sphere.py
safe_autonomy_simulation/sims/inspection/utils/vector.py
safe_autonomy_simulation/sims/spacecraft/__init__.py
safe_autonomy_simulation/sims/spacecraft/defaults.py
safe_autonomy_simulation/sims/spacecraft/point_model.py
safe_autonomy_simulation/sims/spacecraft/rotational_model.py
safe_autonomy_simulation/sims/spacecraft/sixdof_model.py
safe_autonomy_simulation/utils/__init__.py
safe_autonomy_simulation/utils/sets.py
safe_autonomy_simulation-2.2.1.dist-info/METADATA
safe_autonomy_simulation-2.2.1.dist-info/WHEEL
safe_autonomy_simulation-2.2.1.dist-info/licenses/LICENSE
safe_autonomy_simulation-2.2.1.dist-info/RECORD
