Metadata-Version: 2.4
Name: safe-autonomy-simulation
Version: 2.2.1
Summary: A library for building continuous simulation environments, designed to support safe autonomy research.
Author-email: Jamie Cunningham <james.cunningham@udri.udayton.edu>
License-File: LICENSE
Classifier: Operating System :: OS Independent
Classifier: Programming Language :: Python :: 3
Requires-Python: >=3.10
Requires-Dist: diffrax>=0.6.1
Requires-Dist: jax[cpu]>=0.4.30
Requires-Dist: numpy~=1.26.0
Requires-Dist: pint>=0.24.4
Requires-Dist: scikit-learn>=1.6.1
Requires-Dist: scipy>=1.13.1
Requires-Dist: typing-extensions>=4.14.0
